pytrack/__init__.py
pytrack/_version.py
pytrack/analytics/__init__.py
pytrack/analytics/plugins.py
pytrack/analytics/video.py
pytrack/analytics/visualization.py
pytrack/graph/__init__.py
pytrack/graph/distance.py
pytrack/graph/download.py
pytrack/graph/graph.py
pytrack/graph/utils.py
pytrack/matching/__init__.py
pytrack/matching/candidate.py
pytrack/matching/cleaning.py
pytrack/matching/matcher.py
pytrack/matching/mpmatching.py
pytrack/matching/mpmatching_utils.py
pytrack/video/__init__.py
pytrack/video/create_video.py
pytrack/video/streetview.py
PyTrack_lib-2.0.8.dist-info/LICENSE
PyTrack_lib-2.0.8.dist-info/METADATA
PyTrack_lib-2.0.8.dist-info/WHEEL
PyTrack_lib-2.0.8.dist-info/top_level.txt
PyTrack_lib-2.0.8.dist-info/RECORD
