Metadata-Version: 2.1
Name: PyTrack-lib
Version: 2.0.8
Summary: a Map-Matching-based Python Toolbox for Vehicle Trajectory Reconstruction
Home-page: https://github.com/cosbidev/PyTrack
Author: Matteo Tortora
Author-email: m.tortora@unicampus.it
License: BSD-3-Clause-Clear
Classifier: Programming Language :: Python :: 3
Classifier: License :: OSI Approved :: BSD License
Classifier: Operating System :: OS Independent
Classifier: Topic :: Scientific/Engineering :: GIS
Classifier: Topic :: Scientific/Engineering :: Visualization
Classifier: Topic :: Scientific/Engineering :: Physics
Classifier: Topic :: Scientific/Engineering :: Mathematics
Classifier: Topic :: Scientific/Engineering :: Information Analysis
License-File: LICENSE
Requires-Dist: numpy ~=1.23.2
Requires-Dist: pandas ~=1.4.4
Requires-Dist: networkx ~=2.8.6
Requires-Dist: shapely ~=1.8.4
Requires-Dist: pyproj ~=3.3.1
Requires-Dist: requests ~=2.28.1
Requires-Dist: scikit-learn ~=1.1.2
Requires-Dist: folium ~=0.13.0
Requires-Dist: matplotlib ~=3.5.3
Requires-Dist: setuptools ~=65.3.0
Requires-Dist: pydot ~=1.4.2
Requires-Dist: graphviz ~=0.20.1
